<?xml version="1.0" encoding="utf-8" standalone="yes"?>
<document id="Stat. 69-S0-ch556" xmlns:xi="http://www.w3.org/2001/XInclude" xmlns:codified="https://code.dccouncil.us/schemas/codified" xmlns:codify="https://code.dccouncil.us/schemas/codify" xmlns="https://code.dccouncil.us/schemas/dc-library">
  <heading />
  <codified:stub doc="D.C. Code" path="§38-906" />
  <meta>
    <effective>1925-03-04</effective>
    <citations>
      <citation type="law">69th Congress, Session S0, ch. 556</citation>
    </citations>
  </meta>
</document>